Workbook

Sheet Income Statement
A1: BENEFITS MANAGEMENT COMPANY, INC. - FIN 5637 SPRING 2024 - STUDENT FILE
A2: INCOME STATEMENTS
D3: Year Ended
D4: December 31,
B5: (in millions) | C5: Recent Year | D5: Prior Year 1 | E5: Prior Year 2
B6: Revenue | C6: 2728 | D6: 2552 | E6: 2378
B7: Cost of services, exclusive of depreciation and
B8: amortization | C8: 1829 | D8: 1619 | E8: 1493
B9: Depreciation and amortization (related to cost of services) | C9: 65 | D9: 50 | E9: 34
B11: Gross Profit | C11: =+C6-C8-C9 -> 834 | D11: =+D6-D8-D9 -> 883 | E11: =+E6-E8-E9 -> 851
B13: Selling, general and administrative | C13: 461 | D13: 415 | E13: 452
B14: Depreciation and amortization | C14: 226 | D14: 203 | E14: 195
B16: Total operating expenses | C16: =+C13+C14 -> 687 | D16: =+D13+D14 -> 618 | E16: =+E13+E14 -> 647
B17: Operating Income | C17: =+C11-C16 -> 147 | D17: =+D11-D16 -> 265 | E17: =+E11-E16 -> 204
B18: Interest expense | C18: 234 | D18: 224 | E18: 208
B19: Other expense, net | C19: 7 | D19: 3 | E19: 0
B21: (Loss) Income Before Income Tax (Benefit) Expense | C21: =+C17-C18-C19 -> -94 | D21: =+D17-D18-D19 -> 38 | E21: =+E17-E18-E19 -> -4
B22: Income tax (benefit) expense | C22: 9 | D22: 16 | E22: 17
B24: Net (Loss) Income | C24: =+C21-C22 -> -103 | D24: =+D21-D22 -> 22 | E24: =+E21-E22 -> -21
B26: EBITDA | C26: =+C24+C22+C18+C14+C9 -> 431 | D26: =+D24+D22+D18+D14+D9 -> 515 | E26: =+E24+E22+E18+E14+E9 -> 433
B27: Margin | C27: =+C26/C6 -> 0.1579912 | D27: =+D26/D6 -> 0.20180251 | E27: =+E26/E6 -> 0.18208579

Sheet Adjusted EBITDA
A1: =+'Income Statement'!A1 -> BENEFITS MANAGEMENT COMPANY, INC. - FIN 5637 SPRING 2024 - STUDENT FILE
A2: Adjusted EBITDA
D5: Year Ended
D6: December 31,
B7: (in millions) | C7: Recent Year | D7: Prior Year 1 | E7: Prior Year 2
B8: Net (Loss) Income | C8: -103 | D8: 22 | E8: -21
B9: Interest expense | C9: 234 | D9: 224 | E9: 208
B10: Income tax (benefit) expense | C10: 9 | D10: 16 | E10: 17
B11: Depreciation | C11: 91 | D11: 68 | E11: 49
B12: Intangible amortization | C12: 200 | D12: 185 | E12: 180
B14: EBITDA | C14: =SUM(C8:C12) -> 431 | D14: =SUM(D8:D12) -> 515 | E14: =SUM(E8:E12) -> 433
B15: Share-based compensation | C15: 5 | D15: 9 | E15: 14
B16: Spin-off expenses | C16: 0 | D16: 0 | E16: 49
B17: Non-recurring professional expenses | C17: 0 | D17: 14 | E17: 1
B18: Transformation initiatives | C18: 8 | D18: 22 | E18: 52
B19: Restructuring | C19: 77 | D19: 14 | E19: 0
B20: Other non-recurring items | C20: 43 | D20: 22 | E20: 27
B22: Adjusted EBITDA | C22: 564 | D22: 596 | E22: 576
B23: Margin | C23: =+C22/'Income Statement'!C6 -> 0.20674487 | D23: =+D22/'Income Statement'!D6 -> 0.23354232 | E23: =+E22/'Income Statement'!E6 -> 0.24222035

Sheet Balance Sheet
A1: =+'Income Statement'!A1 -> BENEFITS MANAGEMENT COMPANY, INC. - FIN 5637 SPRING 2024 - STUDENT FILE
A2: Balance Sheet
D3: Year Ended
D4: December 31,
B5: (in millions) | C5: Recent Year | D5: Prior Year 1
B6: Assets
B7: Current Assets
B8: Cash and cash equivalents | C8: 506 | D8: 218
B9: Receivables, net | C9: 532 | D9: 665
B10: Other current assets | C10: 163 | D10: 125
B11: Total Current Assets Before Fiduciary Assets | C11: 1201 | D11: 1008
B12: Fiduciary assets | C12: 1030 | D12: 767
B13: Total Current Assets | C13: 2231 | D13: 1775
B15: Goodwill | C15: 2245 | D15: 2214
B16: Intangible assets, net | C16: 1733 | D16: 1932
B17: Fixed assets, net | C17: 334 | D17: 283
B18: Deferred tax assets, net | C18: 5 | D18: 24
B19: Other assets | C19: 408 | D19: 358
B21: Total Assets | C21: 6956 | D21: 6586
B23: Liabilities and Equity
B24: Liabilities
B25: Current Liabilities
B26: Accounts payable and accrued liabilities | C26: 394 | D26: 405
B27: Current portion of long term debt | C27: 37 | D27: 30
B28: Other current liabilities | C28: 324 | D28: 343
B29: Total Current Liabilities Before Fiduciary Liabilities | C29: 755 | D29: 778
B30: Fiduciary liabilities | C30: 1030 | D30: 767
B31: Total Current Liabilities | C31: 1785 | D31: 1545
B33: Deferred tax liabilities | C33: 0 | D33: 12
B34: Long term debt | C34: 4041 | D34: 3770
B35: Other liabilities | C35: 447 | D35: 454
B37: Total Liabilities | C37: 6273 | D37: 5781
B40: Total Equity | C40: 683 | D40: 805
B42: Total Liabilities and Members' Equity | C42: 6956 | D42: 6586

Sheet Valuation EBITDA
A1: =+'Income Statement'!A1 -> BENEFITS MANAGEMENT COMPANY, INC. - FIN 5637 SPRING 2024 - STUDENT FILE
A2: Market Approach Valuation
A4: In millions except for per share amounts
F5: Year Ended | G5: Year Ended
F6: December 31, | G6: December 31,
F7: Recent Year | G7: Prior Year 1
A9: EBITDA | F9: ='Adjusted EBITDA'!C22 -> 564 | G9: ='Adjusted EBITDA'!D22 -> 596
A11: Multiple | F11: 9 | G11: 10
A13: Enterprise Value | F13: =IF(OR(F9=0,F11=0),0,F9*F11) -> 5076 | G13: =IF(OR(G9=0,G11=0),0,G9*G11) -> 5960
A15: Add: Cash | F15: ='Balance Sheet'!C8 -> 506 | G15: ='Balance Sheet'!D8 -> 218
A16: Less: Interest Bearing Debt | F16: ='Balance Sheet'!C27+'Balance Sheet'!C34 -> 4078 | G16: ='Balance Sheet'!D27+'Balance Sheet'!D34 -> 3800
A18: Equity Value | F18: =F13+F15-F16 -> 1504 | G18: =G13+G15-G16 -> 2378
A20: Shares Outstanding | F20: 200 | G20: 200
A22: Value per Share | F22: =IFERROR(F18/F20,0) -> 7.52 | G22: =IFERROR(G18/G20,0) -> 11.89

Sheet Valuation Revenue
A1: =+'Income Statement'!A1 -> BENEFITS MANAGEMENT COMPANY, INC. - FIN 5637 SPRING 2024 - STUDENT FILE
A2: Market Approach Valuation
A4: In millions except for per share amounts
F5: Year Ended | G5: Year Ended
F6: December 31, | G6: December 31,
F7: Recent Year | G7: Prior Year 1
A9: Revenue | F9: ='Income Statement'!C6 -> 2728 | G9: ='Income Statement'!D6 -> 2552
A11: Multiple | F11: 1.5 | G11: 1.7
A13: Enterprise Value | F13: =IF(OR(F9=0,F11=0),0,F9*F11) -> 4092 | G13: =IF(OR(G9=0,G11=0),0,G9*G11) -> 4338.4
A15: Add: Cash | F15: ='Balance Sheet'!C8 -> 506 | G15: ='Balance Sheet'!D8 -> 218
A16: Less: Interest Bearing Debt | F16: ='Balance Sheet'!C27+'Balance Sheet'!C34 -> 4078 | G16: ='Balance Sheet'!D27+'Balance Sheet'!D34 -> 3800
A18: Equity Value | F18: =F13+F15-F16 -> 520 | G18: =G13+G15-G16 -> 756.4
A20: Shares Outstanding | F20: 200 | G20: 200
A22: Value per Share | F22: =IFERROR(F18/F20,0) -> 2.6 | G22: =IFERROR(G18/G20,0) -> 3.782
