Workbook

Sheet Projections
A2: INTANGIBLE ASSET MODELING
A4: Trade Name Valuation - Relief from Royalty Method
A6: ($ in thousands) | C6: Year 1 | D6: Year 2 | E6: Year 3 | F6: Year 4 | G6: Year 5
A7: Sales | C7: 125000 | D7: 132000 | E7: 140000 | F7: 150000 | G7: 165000
A9: Cost of Goods Sold | C9: 81250 | D9: 85800 | E9: 91000 | F9: 97500 | G9: 107250
A11: Gross Profit | C11: =C7-C9 -> 43750 | D11: =D7-D9 -> 46200 | E11: =E7-E9 -> 49000 | F11: =F7-F9 -> 52500 | G11: =G7-G9 -> 57750
A12: Gross Profit Margin | C12: =IFERROR(C11/C7,"-") -> 0.35 | D12: =IFERROR(D11/D7,"-") -> 0.35 | E12: =IFERROR(E11/E7,"-") -> 0.35 | F12: =IFERROR(F11/F7,"-") -> 0.35 | G12: =IFERROR(G11/G7,"-") -> 0.35
A13: SG&A Expenses | C13: 13750 | D13: 14520 | E13: 15400 | F13: 16500 | G13: 18150
A15: EBIT | C15: =C11-C13 -> 30000 | D15: =D11-D13 -> 31680 | E15: =E11-E13 -> 33600 | F15: =F11-F13 -> 36000 | G15: =G11-G13 -> 39600
A16: EBIT Margin | C16: =IFERROR(C15/C7,"-") -> 0.24 | D16: =IFERROR(D15/D7,"-") -> 0.24 | E16: =IFERROR(E15/E7,"-") -> 0.24 | F16: =IFERROR(F15/F7,"-") -> 0.24 | G16: =IFERROR(G15/G7,"-") -> 0.24

Sheet WACC
A1: FIN 5637
A2: INTANGIBLE ASSET MODELING
A4: WACC Calculation
A6: Cost of Equity Inputs
A7: Risk-Free Rate | D7: 0.025
A9: Beta (Levered) | D9: 1.3
A11: Equity Risk Premium | D11: 0.06
A13: Cost of Equity (CAPM) | D13: =D7+D9*D11 -> 0.103 | E13: Rf + Beta * ERP
A15: After-Tax Cost of Debt | D15: 0.045
A17: Capital Structure
A18: Debt Weight | D18: 0.25
A19: Equity Weight | D19: =1-D18 -> 0.75 | E19: 1 - Debt Weight
A20: WACC | D20: =(D18*D15)+(D19*D13) -> 0.0885 | E20: Wd*Kd + We*Ke

Sheet TN
A1: FIN 5637
A2: INTANGIBLE ASSET MODELING EXAMPLE | D2: Relief from Royalty Method
A4: Trade Name Valuation
A6: ($ in thousands) | C6: Year 1 | D6: Year 2 | E6: Year 3 | F6: Year 4 | G6: Year 5 | H6: Perpetuity
A7: Sales | C7: =Projections!C7 -> 125000 | D7: =Projections!D7 -> 132000 | E7: =Projections!E7 -> 140000 | F7: =Projections!F7 -> 150000 | G7: =Projections!G7 -> 165000
A8: Royalty Rate | B8: 0.025
A9: Royalty Savings | C9: =C7*$B$8 -> 3125 | D9: =D7*$B$8 -> 3300 | E9: =E7*$B$8 -> 3500 | F9: =F7*$B$8 -> 3750 | G9: =G7*$B$8 -> 4125
A11: Taxes | B11: 0.25 | C11: =C9*$B$11 -> 781.25 | D11: =D9*$B$11 -> 825 | E11: =E9*$B$11 -> 875 | F11: =F9*$B$11 -> 937.5 | G11: =G9*$B$11 -> 1031.25 | I11: Long-term
A12: After-Tax Royalty Savings | C12: =C9-C11 -> 2343.75 | D12: =D9-D11 -> 2475 | E12: =E9-E11 -> 2625 | F12: =F9-F11 -> 2812.5 | G12: =G9-G11 -> 3093.75 | H12: =G12*(1+I14) -> 3202.0312 | I12: Growth Rate
A13: Terminal Value | H13: =H12/($B$14-$I$14) -> 54735.577 | I13: Assumption
A14: Discount Rate | B14: =WACC!D20+0.005 -> 0.0935 | I14: 0.035
A16: Cash Flow to Discount | C16: =C12/(1+$B$14) -> 2143.3471 | D16: =D12/(1+$B$14) -> 2263.3745 | E16: =E12/(1+$B$14) -> 2400.5487 | F16: =F12/(1+$B$14) -> 2572.0165 | G16: =G12/(1+$B$14)+H13 -> 57564.795
A18: (1) Discount rate = WACC + 0.5% intangible asset risk premium
A20: Valuation Summary
A22: Present Value (NPV) | C22: =NPV(B14,C16:G16) -> 44305.968 | D22: NPV of discounted cash flows
A23: Tax Amortization Benefit (TAB) | C23: =1/(1-B11*((1-POWER(1+B14,-15))/B14)/15) -> 1.1515609 | D23: TAB multiplier (15-yr amortization)
A25: Fair Value of Trade Name | C25: =C22*C23 -> 51021.021 | D25: NPV x TAB
A27: TAB = 1/[1 - TR × ((1-(1+DR)^-n)/DR)/n] | TR=25%, DR=9.35%, n=15 years
