Workbook

Sheet Situation
A1: FIN 5637 CLASSWORK

Sheet Income Statement
A1: FAMILY MARKETS, INC.
A2: INCOME STATEMENTS
A3: For the Fiscal Year Ending ($millions) | B3: Actual 12/31/2021 | C3: Actual 12/31/2022 | D3: Actual 12/31/2023 | E3: Forecast 12/31/2024
A5: Total Revenue | B5: 5345 | C5: 5823 | D5: 6023 | E5: 6425 | F5: 0.067
A7: Cost Of Goods Sold | B7: =+B5*0.752 -> 4019.44 | C7: =+C5*0.756 -> 4402.188 | D7: =+D5*0.757 -> 4559.411 | E7: =+E5*0.758 -> 4870.15
A8: Gross Profit | B8: =+B5-B7 -> 1325.56 | C8: =+C5-C7 -> 1420.812 | D8: =+D5-D7 -> 1463.589 | E8: =+E5-E7 -> 1554.85
A9: Margin | B9: =+B8/B5 -> 0.248 | C9: =+C8/C5 -> 0.244 | D9: =+D8/D5 -> 0.243 | E9: =+E8/E5 -> 0.242
A10: Selling General & Admin Exp. | B10: 934 | C10: 982 | D10: 1025 | E10: 1083
A11: Depreciation & Amortization | B11: 78 | C11: 81 | D11: 86 | E11: 90
A12: One-Time/Unusual Charges | B12: 0 | C12: 17 | D12: 5 | E12: 8
A13: Other Operating Expense/(Income) | B13: 3 | C13: 4 | D13: 2 | E13: 5
A14: Total Operating Expenses | B14: =SUM(B10:B13) -> 1015 | C14: =SUM(C10:C13) -> 1084 | D14: =SUM(D10:D13) -> 1118 | E14: =SUM(E10:E13) -> 1186
A15: Operating Income | B15: =+B8-B14 -> 310.56 | C15: =+C8-C14 -> 336.812 | D15: =+D8-D14 -> 345.589 | E15: =+E8-E14 -> 368.85
A16: Margin | B16: =+B15/B5 -> 0.0581029 | C16: =+C15/C5 -> 0.057841662 | D16: =+D15/D5 -> 0.057378217 | E16: =+E15/E5 -> 0.05740856
A17: Interest Expense | B17: 45 | C17: 38 | D17: 36 | E17: 35
A18: Earnings before Tax | B18: =+B15-B17 -> 265.56 | C18: =+C15-C17 -> 298.812 | D18: =+D15-D17 -> 309.589 | E18: =+E15-E17 -> 333.85
A20: Income Tax Expense | B20: =+B18*0.22 -> 58.4232 | C20: =+C18*0.22 -> 65.73864 | D20: =+D18*0.22 -> 68.10958 | E20: =+E18*0.22 -> 73.447
A21: Net Income | B21: =+B18-B20 -> 207.1368 | C21: =+C18-C20 -> 233.07336 | D21: =+D18-D20 -> 241.47942 | E21: =+E18-E20 -> 260.403
A22: Margin | B22: =+B21/B5 -> 0.038753377 | C22: =+C21/C5 -> 0.040026337 | D22: =+D21/D5 -> 0.040092881 | E22: =+E21/E5 -> 0.04052965
A24: NOTE: WE WILL DISCUSS IMPLICATIONS OF FASB 842 LEASE ACCOUNTING ON THE CALCULATION OF MULTIPLES

Sheet Balance Sheet
A1: =+'Income Statement'!A1 -> FAMILY MARKETS, INC.
A2: ($millions)
A3: Balance Sheet as of: | B3: =+'Income Statement'!B3 -> Actual 12/31/2021 | C3: =+'Income Statement'!C3 -> Actual 12/31/2022 | D3: =+'Income Statement'!D3 -> Actual 12/31/2023 | E3: Most Recent
A4: ASSETS
A5: Cash And Equivalents | B5: 35 | C5: 37 | D5: 34 | E5: 40
A6: Accounts Receivable | B6: 53 | C6: 63 | D6: 65 | E6: 71
A7: Inventory | B7: 399 | C7: 411 | D7: 423 | E7: 436
A8: Other Current Assets | B8: 5 | C8: 5.5 | D8: 5.4 | E8: 6
A9: Total Current Assets | B9: =SUM(B5:B8) -> 492 | C9: =SUM(C5:C8) -> 516.5 | D9: =SUM(D5:D8) -> 527.4 | E9: =SUM(E5:E8) -> 553
A11: Gross Property, Plant & Equipment | B11: 2825 | C11: 2877 | D11: 2912 | E11: 2936
A12: Accumulated Depreciation | B12: -1452 | C12: -1532 | D12: -1605 | E12: -1681
A13: Net Property, Plant & Equipment | B13: =+B11+B12 -> 1373 | C13: =+C11+C12 -> 1345 | D13: =+D11+D12 -> 1307 | E13: =+E11+E12 -> 1255
A14: Operating Lease Right of Use Asset | B14: 48.5 | C14: 49 | D14: 51 | E14: 50.5
A15: Other Long-Term Assets | B15: 8 | C15: 7 | D15: 8 | E15: 10
A16: Total Assets | B16: =+B9+B13+B14+B15 -> 1921.5 | C16: =+C9+C13+C14+C15 -> 1917.5 | D16: =+D9+D13+D14+D15 -> 1893.4 | E16: =+E9+E13+E14+E15 -> 1868.5
A18: LIABILITIES
A19: Accounts Payable | B19: 166 | C19: 193 | D19: 211 | E19: 224
A20: Accrued Expense | B20: 66 | C20: 77 | D20: 82 | E20: 88
A21: Current Portion of Long-Term Debt | B21: 15 | C21: 15 | D21: 15 | E21: 15
A22: Current Portion of Leases | B22: 5 | C22: 5.5 | D22: 5.5 | E22: 6
A23: Other Current Liabilities | B23: 3 | C23: 3.6 | D23: 4.2 | E23: 4
A24: Total Current Liabilities | B24: =SUM(B19:B23) -> 255 | C24: =SUM(C19:C23) -> 294.1 | D24: =SUM(D19:D23) -> 317.7 | E24: =SUM(E19:E23) -> 337
A26: Long-Term Debt | B26: 875 | C26: 855 | D26: 800 | E26: 775
A27: Long-Term Lease Obligations | B27: =+B14-B22 -> 43.5 | C27: =+C14-C22 -> 43.5 | D27: =+D14-D22 -> 45.5 | E27: =+E14-E22 -> 44.5
A28: Other Non-Current Liabilities | B28: 12 | C28: 13.4 | D28: 14.7 | E28: 15
A29: Total Liabilities | B29: =SUM(B24:B28) -> 1185.5 | C29: =SUM(C24:C28) -> 1206 | D29: =SUM(D24:D28) -> 1177.9 | E29: =SUM(E24:E28) -> 1171.5
A31: Common Stock/Paid in Capital | B31: 25 | C31: 25 | D31: 25 | E31: 25
A32: Retained Earnings | B32: =+B16-B29-B31 -> 711 | C32: =+C16-C29-C31 -> 686.5 | D32: =+D16-D29-D31 -> 690.5 | E32: =+E16-E29-E31 -> 672
A33: Total Equity | B33: =+B31+B32 -> 736 | C33: =+C31+C32 -> 711.5 | D33: =+D31+D32 -> 715.5 | E33: =+E31+E32 -> 697
A35: Total Liabilities And Equity | B35: =+B33+B29 -> 1921.5 | C35: =+C33+C29 -> 1917.5 | D35: =+D33+D29 -> 1893.4 | E35: =+E33+E29 -> 1868.5

Sheet Valuation
A1: =+'Income Statement'!A1 -> FAMILY MARKETS, INC.
A2: Valuation Analysis
A3: $ in millions
A5: Multiple of EBITDA
C6: Recent Year | D6: Next Year
A8: EBITDA | C8: ='Income Statement'!D15+'Income Statement'!D11 -> 431.589 | D8: ='Income Statement'!E15+'Income Statement'!E11 -> 458.85
A9: Adjustments | C9: ='Income Statement'!D12 -> 5 | D9: ='Income Statement'!E12 -> 8
A10: Adjusted EBITDA | C10: =C8+C9 -> 436.589 | D10: =D8+D9 -> 466.85
A12: Selected Multiple | C12: 6 | D12: 5.5
A14: Enterprise Value | C14: =C10*C12 -> 2619.534 | D14: =D10*D12 -> 2567.675
A15: Add: Cash | C15: ='Balance Sheet'!E5 -> 40 | D15: 40
A16: Less: Debt | C16: =-'Balance Sheet'!E26-'Balance Sheet'!E21 -> -790 | D16: -790
A18: Common Equity Value | C18: =C14+C15+C16 -> 1869.534 | D18: =D14+D15+D16 -> 1817.675
A19: Shares Outstanding | C19: 50.5 | D19: 50.5 | XFD19: c
A20: Value per Share | C20: =C18/C19 -> 37.020475 | D20: =D18/D19 -> 35.993564
A22: Multiple of Revenue
C23: Recent Year | D23: Next Year
A25: Revenue | C25: ='Income Statement'!D5 -> 6023 | D25: ='Income Statement'!E5 -> 6425
A27: Selected Multiple | C27: 0.5 | D27: 0.45
A29: Enterprise Value | C29: =C25*C27 -> 3011.5 | D29: =D25*D27 -> 2891.25
A30: Add: Cash | C30: ='Balance Sheet'!E5 -> 40 | D30: 40
A31: Less: Debt | C31: =-C16 -> 790 | D31: 790
A33: Common Equity Value | C33: =C29+C30-C31 -> 2261.5 | D33: =D29+D30-D31 -> 2141.25
A34: Shares Outstanding | C34: =C19 -> 50.5 | D34: =D19 -> 50.5
A35: Value per Share | C35: =C33/C34 -> 44.782178 | D35: =D33/D34 -> 42.40099
