Workbook

Sheet Transaction
A3: AMERICAN TOOL CORP.
A4: PRIVATE EQUITY ACQUISITION

Sheet Sources Uses
A1: TRANSACTION - SOURCES AND USES
A2: =Transaction!A3 -> AMERICAN TOOL CORP.
A3: ($ in millions) | F3: Price | G3: 500
F4: BV of Equity | G4: ='Balance Sheet'!B32 -> 140
F5: Excess | G5: =G3-G4 -> 360
B6: Sources
B7: Common equity | F7: =G3*0.6+F14 -> 315
B8: Term debt | F8: 260
B9: Total Sources | F9: =F7+F8 -> 575
F10: =IF(ROUND(F9-F15,2)=0,"✓ Balanced","✗ Out of Balance") -> ✓ Balanced
B11: Uses
B12: Purchase Price - Equity | F12: =G3 -> 500
B13: Repay existing debt | F13: ='Balance Sheet'!B21+'Balance Sheet'!B25 -> 60
B14: Transaction Expenses | F14: 15
B15: Total Uses | F15: =SUM(F12:F14) -> 575
A17: Journal Entries | D17: Debit | E17: Credit
A18: Fixed assets | D18: 60
A19: Identified intangibles | D19: 85
A20: Goodwill | D20: =G5-D18-D19 -> 215
A21: Existing equity | D21: ='Balance Sheet'!B32 -> 140
A22: Current debt | D22: =F13 -> 60
A23: Transaction fees | D23: =F14 -> 15
A24: New senior debt | E24: 260
A25: Common Stock - Equity new | E25: =F7 -> 315
D26: =SUM(D18:D23) -> 575 | E26: =SUM(E24:E25) -> 575
A28: Balance Check: | D28: =IF(ROUND(D26-E26,2)=0,"✓ Balanced","✗ Out of Balance") -> ✓ Balanced

Sheet Balance Sheet
A1: =Transaction!A3 -> AMERICAN TOOL CORP.
A2: OPENING BALANCE SHEET
A3: ($ in millions) | B3: Unadjusted | C3: Debit | D3: Credit | E3: Adjusted
A4: ASSETS
A5: Cash And Equivalents | B5: 25 | E5: =B5 -> 25
A6: Accounts Receivable | B6: 50 | E6: =B6 -> 50
A7: Inventory | B7: 75 | E7: =B7 -> 75
A8: Prepaid Exp. | B8: 5 | E8: =B8 -> 5
A9: Total Current Assets | B9: =SUM(B5:B8) -> 155 | E9: =SUM(E5:E8) -> 155
A11: Net Property, Plant & Equipment | B11: 175 | C11: ='Sources Uses'!D18 -> 60 | E11: =B11+C11 -> 235
A13: Goodwill | B13: 0 | C13: ='Sources Uses'!D20 -> 215 | E13: =C13 -> 215
A14: Identified Intangibles | B14: 10 | C14: ='Sources Uses'!D19 -> 85 | E14: =B14+C14 -> 95
A15: Other Long-Term Assets | B15: 5 | C15: ='Sources Uses'!F14 -> 15 | E15: =B15+C15 -> 20 | F15: (1)
A16: Total Assets | B16: =SUM(B11:B15)+B9 -> 345 | E16: =E9+SUM(E11,E13:E15) -> 720
A18: LIABILITIES
A19: Accounts Payable | B19: 95 | E19: =B19 -> 95
A20: Accrued Exp. | B20: 35 | E20: =B20 -> 35
A21: Current Portion LT Debt | B21: 10 | C21: 10 | E21: =B21-C21 -> 0
A22: Other Current Liabilities | B22: 5 | E22: =B22 -> 5
A23: Total Current Liabilities | B23: =SUM(B19:B22) -> 145 | E23: =SUM(E19:E22) -> 135
A25: Long-Term Debt | B25: 50 | C25: 50 | E25: =B25-C25 -> 0
A26: New Term Loan | D26: ='Sources Uses'!E24 -> 260 | E26: =D26 -> 260
A27: Other Non-Current Liabilities | B27: 10 | E27: =B27 -> 10
A28: Total Liabilities | B28: =SUM(B23:B27) -> 205 | E28: =E23+SUM(E25:E27) -> 405
A29: SHAREHOLDERS' EQUITY
A30: Common Stock | B30: 20 | C30: 20 | D30: ='Sources Uses'!E25 -> 315 | E30: =D30 -> 315
A31: Retained Earnings | B31: 120 | C31: 120 | E31: =B31-C31 -> 0
A32: Total Equity | B32: =SUM(B30:B31) -> 140 | E32: =SUM(E30:E31) -> 315
A34: Total Liabilities And Equity | B34: =B28+B32 -> 345 | E34: =E28+E32 -> 720
A35: (1) Note transaction fees will be written off and expensed in the year of the transaction.
A37: Balance Check: | E37: =IF(ROUND(E16-E34,2)=0,"✓ Balanced","✗ Out of Balance by "&TEXT(E16-E34,"$#,##0")) -> ✓ Balanced
